py2qan/__init__.py
py2qan/_version.py
py2qan/bench_arch.py
py2qan/heuristic_mapper.py
py2qan/qrouter_depth.py
py2qan/scheduler.py
py2QAN-0.0.3.dist-info/LICENSE
py2QAN-0.0.3.dist-info/METADATA
py2QAN-0.0.3.dist-info/WHEEL
py2QAN-0.0.3.dist-info/top_level.txt
py2QAN-0.0.3.dist-info/RECORD
