Metadata-Version: 2.1
Name: py2QAN
Version: 0.0.3
Summary: 2QAN is an open source compiler for two-local qubit Hamiltonian simulation algorithms.
Home-page: https://github.com/lllingoo/2QAN
Author: Lingling Lao
Author-email: laolinglingrolls@gmail.com
License: UNKNOWN
Platform: UNKNOWN
Classifier: Programming Language :: Python :: 3
Classifier: License :: OSI Approved :: Apache Software License
Classifier: Topic :: Scientific/Engineering
Requires-Python: >=3.8
Requires-Dist: numpy (~=1.22.3)
Requires-Dist: qiskit (~=0.36.0)
Requires-Dist: networkx (~=2.5)
